Workbook

Sheet Assumptions
A1: Vendor Cost Comparison - Replacement Centrifugal Pumps (P-101A/B)
A2: Unit 100 - Feed Pump Package | Procurement Ref: PR-2026-0341
A4: Key Assumptions
A5: Number of pump sets required | B5: 2
A6: Evaluation period (years) | B6: 10
A7: Discount rate (for NPV) | B7: 0.1
A8: Electricity tariff | B8: 8.5
A9: Operating hours per year | B9: 8000
A10: USD to INR rate (for imported vendor) | B10: 84
A12: Note: Blue = input (edit here). Black = formula (do not overwrite). Yellow fill = assumption to confirm before issuing PO.

Sheet Vendor Quotes
A2: Line Item | B2: Vendor A - Kirloskar | C2: Vendor B - Grundfos (Import) | D2: Vendor C - WPIL | E2: Notes
A3: Base equipment price per set (Rs.) | B3: 1850000 | C3: 2100000 | D3: 1720000 | E3: As per quotation, ex-works
A4: Freight & insurance (Rs. per set) | B4: 25000 | C4: 95000 | D4: 30000 | E4: Vendor B is imported (EU)
A5: Installation & commissioning (Rs. per set) | B5: 120000 | C5: 150000 | D5: 110000
A6: Number of pump sets | B6: =Assumptions!$B$5 -> 2 | C6: =Assumptions!$B$5 -> 2 | D6: =Assumptions!$B$5 -> 2 | E6: Linked to Assumptions
A7: Rated motor power (kW) | B7: 45 | C7: 42 | D7: 47 | E7: Affects running cost
A8: Rated efficiency (%) | B8: 0.78 | C8: 0.84 | D8: 0.76 | E8: Vendor B highest efficiency
A9: Warranty period (months) | B9: 12 | C9: 24 | D9: 12
A10: Annual AMC cost after warranty (Rs.) | B10: 65000 | C10: 55000 | D10: 70000 | E10: Per set, post-warranty
A11: Spares kit (2 yrs) price (Rs.) | B11: 180000 | C11: 240000 | D11: 165000 | E11: Recommended spares per vendor
A12: Delivery lead time (weeks) | B12: 10 | C12: 16 | D12: 8

Sheet TCO Comparison
A1: 10-Year Total Cost of Ownership Comparison
A3: Cost Component | B3: Vendor A - Kirloskar | C3: Vendor B - Grundfos (Import) | D3: Vendor C - WPIL
A4: Capital Cost
A5: Equipment + Freight + Install, all sets | B5: =('Vendor Quotes'!B3+'Vendor Quotes'!B4+'Vendor Quotes'!B5)*'Vendor Quotes'!B6 -> 3990000 | C5: =('Vendor Quotes'!C3+'Vendor Quotes'!C4+'Vendor Quotes'!C5)*'Vendor Quotes'!C6 -> 4690000 | D5: =('Vendor Quotes'!D3+'Vendor Quotes'!D4+'Vendor Quotes'!D5)*'Vendor Quotes'!D6 -> 3720000
A6: Spares kit, all sets | B6: ='Vendor Quotes'!B11*'Vendor Quotes'!B6 -> 360000 | C6: ='Vendor Quotes'!C11*'Vendor Quotes'!C6 -> 480000 | D6: ='Vendor Quotes'!D11*'Vendor Quotes'!D6 -> 330000
A7: Subtotal - Capital Cost | B7: =SUM(B5:B6) -> 4350000 | C7: =SUM(C5:C6) -> 5170000 | D7: =SUM(D5:D6) -> 4050000
A9: Operating Cost (10-year, undiscounted)
A10: Annual energy cost per set (Rs.) | B10: ='Vendor Quotes'!B7*Assumptions!$B$9*Assumptions!$B$8 -> 3060000 | C10: ='Vendor Quotes'!C7*Assumptions!$B$9*Assumptions!$B$8 -> 2856000 | D10: ='Vendor Quotes'!D7*Assumptions!$B$9*Assumptions!$B$8 -> 3196000
A11: 10-yr energy cost, all sets | B11: =B10*'Vendor Quotes'!B6*Assumptions!$B$6 -> 61200000 | C11: =C10*'Vendor Quotes'!C6*Assumptions!$B$6 -> 57120000 | D11: =D10*'Vendor Quotes'!D6*Assumptions!$B$6 -> 63920000
A12: 10-yr AMC cost, all sets (post-warranty years) | B12: ='Vendor Quotes'!B10*'Vendor Quotes'!B6*(Assumptions!$B$6-'Vendor Quotes'!B9/12) -> 1170000 | C12: ='Vendor Quotes'!C10*'Vendor Quotes'!C6*(Assumptions!$B$6-'Vendor Quotes'!C9/12) -> 880000 | D12: ='Vendor Quotes'!D10*'Vendor Quotes'!D6*(Assumptions!$B$6-'Vendor Quotes'!D9/12) -> 1260000
A13: Subtotal - 10-yr Operating Cost | B13: =SUM(B10:B12)-B10 -> 62370000 | C13: =SUM(C10:C12)-C10 -> 58000000 | D13: =SUM(D10:D12)-D10 -> 65180000
A15: TOTAL COST OF OWNERSHIP (10-yr) | B15: =B7+B13 -> 66720000 | C15: =C7+C13 -> 63170000 | D15: =D7+D13 -> 69230000
A17: Ranking (1 = lowest TCO) | B17: =RANK(B15,$B$15:$D$15,1) -> 2 | C17: =RANK(C15,$B$15:$D$15,1) -> 1 | D17: =RANK(D15,$B$15:$D$15,1) -> 3
A20: Assumption: energy cost = rated power x efficiency-adjusted load x tariff x hours;
A21: AMC applies for years remaining after each vendor's warranty period. Figures are illustrative test data, not actual vendor quotes.
